django_announcement/__init__.py
django_announcement/admin/__init__.py
django_announcement/admin/announcement.py
django_announcement/admin/announcement_profile.py
django_announcement/admin/audience.py
django_announcement/admin/audience_announce.py
django_announcement/admin/category.py
django_announcement/admin/inlines.py
django_announcement/admin/user_audience.py
django_announcement/api/__init__.py
django_announcement/api/filters/__init__.py
django_announcement/api/filters/announcement_filter.py
django_announcement/api/paginations/__init__.py
django_announcement/api/paginations/limit_offset_pagination.py
django_announcement/api/routers/__init__.py
django_announcement/api/routers/announcement.py
django_announcement/api/serializers/__init__.py
django_announcement/api/serializers/announcement.py
django_announcement/api/serializers/audience.py
django_announcement/api/serializers/base.py
django_announcement/api/serializers/category.py
django_announcement/api/throttlings/__init__.py
django_announcement/api/throttlings/role_base_throttle.py
django_announcement/api/views/__init__.py
django_announcement/api/views/announcement.py
django_announcement/apps.py
django_announcement/constants/__init__.py
django_announcement/constants/default_settings.py
django_announcement/constants/types.py
django_announcement/management/__init__.py
django_announcement/management/commands/__init__.py
django_announcement/management/commands/generate_audiences.py
django_announcement/management/commands/generate_profiles.py
django_announcement/migrations/0001_initial.py
django_announcement/migrations/__init__.py
django_announcement/mixins/__init__.py
django_announcement/mixins/admin/__init__.py
django_announcement/mixins/admin/base.py
django_announcement/mixins/admin/form_fields.py
django_announcement/mixins/admin/inlines.py
django_announcement/mixins/admin/permission.py
django_announcement/mixins/config_api_attrs.py
django_announcement/mixins/control_api_methods.py
dj_announcement_api-1.0.0.dist-info/AUTHORS.md
dj_announcement_api-1.0.0.dist-info/LICENSE
dj_announcement_api-1.0.0.dist-info/METADATA
dj_announcement_api-1.0.0.dist-info/WHEEL
dj_announcement_api-1.0.0.dist-info/RECORD
